pyepsalarm/__init__.py
pyepsalarm/pyepsalarm.py
pyepsalarm-1.0.1.dist-info/LICENSE
pyepsalarm-1.0.1.dist-info/METADATA
pyepsalarm-1.0.1.dist-info/WHEEL
pyepsalarm-1.0.1.dist-info/top_level.txt
pyepsalarm-1.0.1.dist-info/RECORD
