Metadata-Version: 2.1
Name: pyepsalarm
Version: 1.0.1
Summary: A simple library to interface with EPS systems, built for use with Home-Assistant
Home-page: https://github.com/parvarm/pyepsalarm
Download-URL: https://github.com/parvarm/pyepsalarm
Author: Parv Arm
Author-email: parvarm@outlook.fr
License: Apache 2.0
Keywords: eps,homiris,alarm,hass,home assistant
Classifier: Development Status :: 4 - Beta
Classifier: Intended Audience :: Developers
Classifier: Programming Language :: Python :: 3
License-File: LICENSE
Requires-Dist: requests >=2.0.0
